{
  "file_name": "福島6R.csv",
  "race_number": "福島6R",
  "race_name": "１勝ｸﾗｽ・若",
  "race_class": "1勝",
  "date": "2025/11/08",
  "year": 2025,
  "month": 11,
  "day": 8,
  "place": "福島",
  "round": 6,
  "surface": "芝",
  "distance": 1800,
  "condition": "３歳以上・１勝クラス/500万下(定量)(若手)",
  "num_horses": 16,
  "meeting": "3福1",
  "horses": [
    {
      "frame": 3,
      "horse_number": 6,
      "horse_name": "スナークピカソ",
      "mark": "",
      "jockey": {
        "name": "小沢大仁",
        "weight": 56.0,
        "weight_reduction": "",
        "this_year": {
          "wins": 30,
          "win_rate": 5.4,
          "place_rate": 10.8,
          "show_rate": 18.1
        },
        "last_year": {
          "wins": 24,
          "win_rate": 4.2,
          "place_rate": 8.2,
          "show_rate": 14.2
        }
      },
      "trainer": {
        "affiliation": "(栗)",
        "name": "高橋一哉",
        "this_year": {
          "wins": 13,
          "win_rate": 6.0,
          "place_rate": 13.8,
          "show_rate": 20.6
        },
        "last_year": {
          "wins": 6,
          "win_rate": 3.7,
          "place_rate": 6.1,
          "show_rate": 10.4
        }
      },
      "interval": 19,
      "zi_index": 111.0,
      "time_mining": 107.84,
      "battle_mining": 71.4,
      "past_races": [
        {
          "date": "2025.6.29",
          "race_name": "ラジオNIＨG3",
          "place": "福島",
          "surface": "芝",
          "distance": "1800",
          "track_condition": "良",
          "frame": "3",
          "horse_number": "3",
          "weight": 53.0,
          "weight_reduction": "",
          "rank": "8",
          "margin": 0.6,
          "corrected_time": 103.0,
          "running_style": "先",
          "last_3f": 35.8,
          "ave_3f": 35.85,
          "pci": 50.1,
          "position_3f": 0.2
        },
        {
          "date": "2025.6.1",
          "race_name": "白百合Ｓ(L)",
          "place": "京都",
          "surface": "芝",
          "distance": "1800",
          "track_condition": "良",
          "frame": "2",
          "horse_number": "2",
          "weight": 57.0,
          "weight_reduction": "",
          "rank": "6",
          "margin": 0.5,
          "corrected_time": 100.0,
          "running_style": "逃",
          "last_3f": 35.9,
          "ave_3f": 34.95,
          "pci": 47.4,
          "position_3f": 0.0
        },
        {
          "date": "2025.3.16",
          "race_name": "スプリンG2",
          "place": "中山",
          "surface": "芝",
          "distance": "1800",
          "track_condition": "重",
          "frame": "8",
          "horse_number": "11",
          "weight": 57.0,
          "weight_reduction": "",
          "rank": "6",
          "margin": 0.6,
          "corrected_time": 102.0,
          "running_style": "中",
          "last_3f": 38.0,
          "ave_3f": 37.05,
          "pci": 47.5,
          "position_3f": 0.7
        },
        {
          "date": "2025.2.22",
          "race_name": "未勝利",
          "place": "小倉",
          "surface": "芝",
          "distance": "1800",
          "track_condition": "良",
          "frame": "3",
          "horse_number": "6",
          "weight": 57.0,
          "weight_reduction": "",
          "rank": "1",
          "margin": -0.1,
          "corrected_time": 89.0,
          "running_style": "先",
          "last_3f": 35.8,
          "ave_3f": 36.6,
          "pci": 52.2,
          "position_3f": 0.1
        },
        {
          "date": "2025.2.2",
          "race_name": "未勝利・若",
          "place": "小倉",
          "surface": "芝",
          "distance": "1800",
          "track_condition": "重",
          "frame": "4",
          "horse_number": "5",
          "weight": 56.0,
          "weight_reduction": "☆",
          "rank": "2",
          "margin": 0.2,
          "corrected_time": 86.0,
          "running_style": "逃",
          "last_3f": 36.4,
          "ave_3f": 37.1,
          "pci": 51.9,
          "position_3f": 0.0
        },
        {
          "date": "2024.10.26",
          "race_name": "未勝利*",
          "place": "京都",
          "surface": "芝",
          "distance": "1600",
          "track_condition": "良",
          "frame": "2",
          "horse_number": "2",
          "weight": 56.0,
          "weight_reduction": "",
          "rank": "5",
          "margin": 0.7,
          "corrected_time": 83.0,
          "running_style": "中",
          "last_3f": 35.2,
          "ave_3f": 35.88,
          "pci": 51.9,
          "position_3f": 0.6
        },
        {
          "date": "2024.9.22",
          "race_name": "未勝利*",
          "place": "中京",
          "surface": "ダ",
          "distance": "1800",
          "track_condition": "良",
          "frame": "8",
          "horse_number": "11",
          "weight": 55.0,
          "weight_reduction": "",
          "rank": "8",
          "margin": 3.0,
          "corrected_time": 63.0,
          "running_style": "中",
          "last_3f": 41.4,
          "ave_3f": 38.45,
          "pci": 42.9,
          "position_3f": 0.6
        },
        {
          "date": "2024.8.24",
          "race_name": "未勝利*",
          "place": "中京",
          "surface": "芝",
          "distance": "1600",
          "track_condition": "良",
          "frame": "8",
          "horse_number": "8",
          "weight": 54.0,
          "weight_reduction": "☆",
          "rank": "3",
          "margin": 0.3,
          "corrected_time": 84.0,
          "running_style": "中",
          "last_3f": 35.3,
          "ave_3f": 36.18,
          "pci": 52.5,
          "position_3f": 0.5
        },
        {
          "date": "2024.8.3",
          "race_name": "新馬",
          "place": "新潟",
          "surface": "芝",
          "distance": "1600",
          "track_condition": "良",
          "frame": "6",
          "horse_number": "6",
          "weight": 54.0,
          "weight_reduction": "☆",
          "rank": "4",
          "margin": 1.1,
          "corrected_time": 80.0,
          "running_style": "中",
          "last_3f": 33.6,
          "ave_3f": 38.04,
          "pci": 63.2,
          "position_3f": 0.8
        }
      ],
      "indices": {
        "mining_index": 66.82,
        "corrected_time_deviation": 64.56,
        "zi_deviation": 65.94,
        "base_score": 66.01,
        "jockey_coefficient": 0.99516,
        "similarity_coefficient": 1.0055,
        "stability_coefficient": 0.99762,
        "total_coefficient_score": 0.001,
        "final_score": 67.98
      }
    },
    {
      "frame": 6,
      "horse_number": 12,
      "horse_name": "ゲンジ",
      "mark": "*",
      "jockey": {
        "name": "河原田菜",
        "weight": 52.0,
        "weight_reduction": "★",
        "this_year": {
          "wins": 3,
          "win_rate": 1.3,
          "place_rate": 3.8,
          "show_rate": 5.0
        },
        "last_year": {
          "wins": 7,
          "win_rate": 1.9,
          "place_rate": 5.7,
          "show_rate": 9.3
        }
      },
      "trainer": {
        "affiliation": "(美)",
        "name": "尾形和幸",
        "this_year": {
          "wins": 12,
          "win_rate": 5.4,
          "place_rate": 10.3,
          "show_rate": 17.5
        },
        "last_year": {
          "wins": 20,
          "win_rate": 8.2,
          "place_rate": 12.3,
          "show_rate": 18.1
        }
      },
      "interval": 6,
      "zi_index": 116.0,
      "time_mining": 109.07,
      "battle_mining": 70.6,
      "past_races": [
        {
          "date": "2025.9.27",
          "race_name": "１勝ｸﾗｽ",
          "place": "中山",
          "surface": "芝",
          "distance": "2200",
          "track_condition": "良",
          "frame": "2",
          "horse_number": "3",
          "weight": 52.0,
          "weight_reduction": "▲",
          "rank": "8",
          "margin": 1.1,
          "corrected_time": 92.0,
          "running_style": "先",
          "last_3f": 35.3,
          "ave_3f": 36.86,
          "pci": 54.4,
          "position_3f": 0.3
        },
        {
          "date": "2025.9.13",
          "race_name": "１勝ｸﾗｽ",
          "place": "中山",
          "surface": "芝",
          "distance": "2000",
          "track_condition": "稍",
          "frame": "3",
          "horse_number": "5",
          "weight": 52.0,
          "weight_reduction": "▲",
          "rank": "2",
          "margin": 0.1,
          "corrected_time": 100.0,
          "running_style": "先",
          "last_3f": 33.9,
          "ave_3f": 37.11,
          "pci": 59.5,
          "position_3f": 0.2
        },
        {
          "date": "2025.7.5",
          "race_name": "伊達特別･1勝",
          "place": "福島",
          "surface": "芝",
          "distance": "2000",
          "track_condition": "良",
          "frame": "2",
          "horse_number": "2",
          "weight": 55.0,
          "weight_reduction": "",
          "rank": "2",
          "margin": 0.3,
          "corrected_time": 98.0,
          "running_style": "後",
          "last_3f": 34.9,
          "ave_3f": 37.24,
          "pci": 56.7,
          "position_3f": 1.8
        },
        {
          "date": "2025.6.15",
          "race_name": "八雲特別･1勝",
          "place": "函館",
          "surface": "芝",
          "distance": "1800",
          "track_condition": "良",
          "frame": "7",
          "horse_number": "10",
          "weight": 55.0,
          "weight_reduction": "",
          "rank": "11",
          "margin": 1.2,
          "corrected_time": 88.0,
          "running_style": "先",
          "last_3f": 36.5,
          "ave_3f": 35.65,
          "pci": 47.7,
          "position_3f": 0.1
        },
        {
          "date": "2025.4.6",
          "race_name": "１勝ｸﾗｽ*",
          "place": "中山",
          "surface": "芝",
          "distance": "1600",
          "track_condition": "良",
          "frame": "1",
          "horse_number": "1",
          "weight": 57.0,
          "weight_reduction": "",
          "rank": "2",
          "margin": 0.3,
          "corrected_time": 99.0,
          "running_style": "後",
          "last_3f": 34.0,
          "ave_3f": 36.3,
          "pci": 56.8,
          "position_3f": 0.8
        },
        {
          "date": "2025.3.22",
          "race_name": "１勝ｸﾗｽ*",
          "place": "中山",
          "surface": "芝",
          "distance": "1600",
          "track_condition": "良",
          "frame": "8",
          "horse_number": "10",
          "weight": 53.0,
          "weight_reduction": "★",
          "rank": "7",
          "margin": 0.4,
          "corrected_time": 95.0,
          "running_style": "先",
          "last_3f": 36.2,
          "ave_3f": 35.58,
          "pci": 48.3,
          "position_3f": 0.2
        },
        {
          "date": "2025.1.26",
          "race_name": "未勝利",
          "place": "小倉",
          "surface": "芝",
          "distance": "1800",
          "track_condition": "良",
          "frame": "1",
          "horse_number": "1",
          "weight": 53.0,
          "weight_reduction": "★",
          "rank": "1",
          "margin": -0.6,
          "corrected_time": 90.0,
          "running_style": "逃",
          "last_3f": 36.3,
          "ave_3f": 36.3,
          "pci": 50.0,
          "position_3f": 0.0
        },
        {
          "date": "2024.12.1",
          "race_name": "新馬",
          "place": "中山",
          "surface": "芝",
          "distance": "2000",
          "track_condition": "良",
          "frame": "3",
          "horse_number": "6",
          "weight": 56.0,
          "weight_reduction": "",
          "rank": "7",
          "margin": 1.1,
          "corrected_time": 82.0,
          "running_style": "先",
          "last_3f": 35.3,
          "ave_3f": 37.24,
          "pci": 55.5,
          "position_3f": 0.1
        }
      ],
      "indices": {
        "mining_index": 61.16,
        "corrected_time_deviation": 62.71,
        "zi_deviation": 71.93,
        "base_score": 63.24,
        "jockey_coefficient": 0.97586,
        "similarity_coefficient": 1.0063,
        "stability_coefficient": 0.997,
        "total_coefficient_score": -0.002,
        "final_score": 60.83
      }
    },
    {
      "frame": 2,
      "horse_number": 3,
      "horse_name": "サングラデーション",
      "mark": "*",
      "jockey": {
        "name": "松本大輝",
        "weight": 57.0,
        "weight_reduction": "☆",
        "this_year": {
          "wins": 18,
          "win_rate": 6.7,
          "place_rate": 12.2,
          "show_rate": 15.6
        },
        "last_year": {
          "wins": 8,
          "win_rate": 4.0,
          "place_rate": 9.1,
          "show_rate": 14.1
        }
      },
      "trainer": {
        "affiliation": "(美)",
        "name": "千葉直人",
        "this_year": {
          "wins": 13,
          "win_rate": 6.2,
          "place_rate": 14.8,
          "show_rate": 27.1
        },
        "last_year": {
          "wins": 8,
          "win_rate": 5.3,
          "place_rate": 10.6,
          "show_rate": 17.2
        }
      },
      "interval": 3,
      "zi_index": 94.0,
      "time_mining": 108.62,
      "battle_mining": 46.1,
      "past_races": [
        {
          "date": "2025.10.19",
          "race_name": "松浜特別･1勝",
          "place": "新潟",
          "surface": "芝",
          "distance": "2000",
          "track_condition": "稍",
          "frame": "5",
          "horse_number": "8",
          "weight": 58.0,
          "weight_reduction": "",
          "rank": "10",
          "margin": 1.1,
          "corrected_time": 93.0,
          "running_style": "中",
          "last_3f": 35.2,
          "ave_3f": 36.56,
          "pci": 53.9,
          "position_3f": 0.7
        },
        {
          "date": "2025.8.24",
          "race_name": "ルスツ特･1勝",
          "place": "札幌",
          "surface": "芝",
          "distance": "2000",
          "track_condition": "良",
          "frame": "6",
          "horse_number": "9",
          "weight": 58.0,
          "weight_reduction": "",
          "rank": "10",
          "margin": 2.3,
          "corrected_time": 80.0,
          "running_style": "先",
          "last_3f": 38.5,
          "ave_3f": 36.47,
          "pci": 44.7,
          "position_3f": 0.1
        },
        {
          "date": "2025.6.29",
          "race_name": "臥牛山特･1勝",
          "place": "函館",
          "surface": "芝",
          "distance": "2000",
          "track_condition": "良",
          "frame": "5",
          "horse_number": "5",
          "weight": 58.0,
          "weight_reduction": "",
          "rank": "4",
          "margin": 0.8,
          "corrected_time": 96.0,
          "running_style": "中",
          "last_3f": 35.1,
          "ave_3f": 36.34,
          "pci": 53.5,
          "position_3f": 0.8
        },
        {
          "date": "2025.6.14",
          "race_name": "奥尻特別･1勝",
          "place": "函館",
          "surface": "芝",
          "distance": "2000",
          "track_condition": "良",
          "frame": "4",
          "horse_number": "4",
          "weight": 58.0,
          "weight_reduction": "",
          "rank": "6",
          "margin": 0.6,
          "corrected_time": 98.0,
          "running_style": "中",
          "last_3f": 34.3,
          "ave_3f": 37.07,
          "pci": 58.1,
          "position_3f": 1.0
        },
        {
          "date": "2025.4.26",
          "race_name": "飯盛山特･1勝",
          "place": "福島",
          "surface": "芝",
          "distance": "2000",
          "track_condition": "良",
          "frame": "4",
          "horse_number": "5",
          "weight": 58.0,
          "weight_reduction": "",
          "rank": "4",
          "margin": 0.7,
          "corrected_time": 97.0,
          "running_style": "中",
          "last_3f": 35.4,
          "ave_3f": 36.26,
          "pci": 52.4,
          "position_3f": 0.6
        },
        {
          "date": "2025.4.13",
          "race_name": "１勝ｸﾗｽ・若",
          "place": "福島",
          "surface": "芝",
          "distance": "2000",
          "track_condition": "良",
          "frame": "1",
          "horse_number": "2",
          "weight": 57.0,
          "weight_reduction": "☆",
          "rank": "3",
          "margin": 0.6,
          "corrected_time": 96.0,
          "running_style": "先",
          "last_3f": 36.0,
          "ave_3f": 36.73,
          "pci": 52.0,
          "position_3f": 0.8
        },
        {
          "date": "2025.2.9",
          "race_name": "１勝ｸﾗｽ",
          "place": "小倉",
          "surface": "芝",
          "distance": "2000",
          "track_condition": "稍",
          "frame": "2",
          "horse_number": "3",
          "weight": 58.0,
          "weight_reduction": "",
          "rank": "6",
          "margin": 0.7,
          "corrected_time": 94.0,
          "running_style": "中",
          "last_3f": 36.6,
          "ave_3f": 36.94,
          "pci": 50.9,
          "position_3f": 1.4
        },
        {
          "date": "2025.1.25",
          "race_name": "１勝ｸﾗｽ",
          "place": "小倉",
          "surface": "芝",
          "distance": "2600",
          "track_condition": "良",
          "frame": "3",
          "horse_number": "6",
          "weight": 58.0,
          "weight_reduction": "",
          "rank": "9",
          "margin": 1.2,
          "corrected_time": 88.0,
          "running_style": "先",
          "last_3f": 37.1,
          "ave_3f": 37.02,
          "pci": 49.8,
          "position_3f": 0.2
        },
        {
          "date": "2024.11.17",
          "race_name": "磐梯山特･1勝",
          "place": "福島",
          "surface": "芝",
          "distance": "2600",
          "track_condition": "良",
          "frame": "1",
          "horse_number": "1",
          "weight": 58.0,
          "weight_reduction": "",
          "rank": "7",
          "margin": 0.8,
          "corrected_time": 92.0,
          "running_style": "中",
          "last_3f": 36.9,
          "ave_3f": 37.77,
          "pci": 52.4,
          "position_3f": 0.6
        },
        {
          "date": "2024.9.16",
          "race_name": "１勝ｸﾗｽ",
          "place": "中山",
          "surface": "ダ",
          "distance": "2400",
          "track_condition": "良",
          "frame": "4",
          "horse_number": "4",
          "weight": 58.0,
          "weight_reduction": "",
          "rank": "8",
          "margin": 2.0,
          "corrected_time": 83.0,
          "running_style": "後",
          "last_3f": 40.0,
          "ave_3f": 39.87,
          "pci": 49.7,
          "position_3f": 0.9
        }
      ],
      "indices": {
        "mining_index": 47.73,
        "corrected_time_deviation": 54.68,
        "zi_deviation": 45.58,
        "base_score": 49.49,
        "jockey_coefficient": 0.99293,
        "similarity_coefficient": 1.00976,
        "stability_coefficient": 0.99401,
        "total_coefficient_score": 0.002,
        "final_score": 51.63
      }
    },
    {
      "frame": 8,
      "horse_number": 16,
      "horse_name": "ニシノエピカリ",
      "mark": "*",
      "jockey": {
        "name": "横山琉人",
        "weight": 54.0,
        "weight_reduction": "",
        "this_year": {
          "wins": 26,
          "win_rate": 6.0,
          "place_rate": 10.6,
          "show_rate": 16.4
        },
        "last_year": {
          "wins": 15,
          "win_rate": 4.6,
          "place_rate": 9.1,
          "show_rate": 14.9
        }
      },
      "trainer": {
        "affiliation": "(美)",
        "name": "手塚貴久",
        "this_year": {
          "wins": 30,
          "win_rate": 11.4,
          "place_rate": 20.5,
          "show_rate": 30.3
        },
        "last_year": {
          "wins": 34,
          "win_rate": 10.3,
          "place_rate": 23.3,
          "show_rate": 31.8
        }
      },
      "interval": 5,
      "zi_index": 92.0,
      "time_mining": 109.22,
      "battle_mining": 56.5,
      "past_races": [
        {
          "date": "2025.10.4",
          "race_name": "１勝ｸﾗｽ・牝",
          "place": "東京",
          "surface": "芝",
          "distance": "2000",
          "track_condition": "良",
          "frame": "5",
          "horse_number": "5",
          "weight": 51.0,
          "weight_reduction": "▲",
          "rank": "9",
          "margin": 1.1,
          "corrected_time": 89.0,
          "running_style": "逃",
          "last_3f": 33.9,
          "ave_3f": 37.71,
          "pci": 61.3,
          "position_3f": 0.4
        },
        {
          "date": "2025.9.7",
          "race_name": "１勝ｸﾗｽ・牝",
          "place": "札幌",
          "surface": "芝",
          "distance": "1800",
          "track_condition": "稍",
          "frame": "8",
          "horse_number": "13",
          "weight": 50.0,
          "weight_reduction": "▲",
          "rank": "3",
          "margin": 0.3,
          "corrected_time": 96.0,
          "running_style": "中",
          "last_3f": 38.5,
          "ave_3f": 36.3,
          "pci": 44.3,
          "position_3f": 1.2
        },
        {
          "date": "2025.5.24",
          "race_name": "カーネー･1勝",
          "place": "東京",
          "surface": "芝",
          "distance": "1800",
          "track_condition": "良",
          "frame": "2",
          "horse_number": "2",
          "weight": 55.0,
          "weight_reduction": "",
          "rank": "8",
          "margin": 2.2,
          "corrected_time": 87.0,
          "running_style": "先",
          "last_3f": 35.9,
          "ave_3f": 35.85,
          "pci": 49.9,
          "position_3f": 0.4
        },
        {
          "date": "2025.3.30",
          "race_name": "ミモザ賞･1勝",
          "place": "中山",
          "surface": "芝",
          "distance": "2000",
          "track_condition": "良",
          "frame": "3",
          "horse_number": "3",
          "weight": 55.0,
          "weight_reduction": "",
          "rank": "7",
          "margin": 1.5,
          "corrected_time": 89.0,
          "running_style": "後",
          "last_3f": 36.8,
          "ave_3f": 36.86,
          "pci": 50.2,
          "position_3f": 0.3
        },
        {
          "date": "2025.1.12",
          "race_name": "未勝利",
          "place": "中山",
          "surface": "芝",
          "distance": "2000",
          "track_condition": "良",
          "frame": "8",
          "horse_number": "16",
          "weight": 55.0,
          "weight_reduction": "",
          "rank": "1",
          "margin": -0.1,
          "corrected_time": 91.0,
          "running_style": "先",
          "last_3f": 35.9,
          "ave_3f": 36.9,
          "pci": 52.8,
          "position_3f": 0.2
        },
        {
          "date": "2024.12.14",
          "race_name": "未勝利・牝*",
          "place": "中山",
          "surface": "芝",
          "distance": "1800",
          "track_condition": "良",
          "frame": "3",
          "horse_number": "6",
          "weight": 55.0,
          "weight_reduction": "",
          "rank": "2",
          "margin": 0.0,
          "corrected_time": 91.0,
          "running_style": "先",
          "last_3f": 35.4,
          "ave_3f": 36.4,
          "pci": 52.8,
          "position_3f": 0.1
        },
        {
          "date": "2024.11.2",
          "race_name": "未勝利・牝*",
          "place": "東京",
          "surface": "芝",
          "distance": "1600",
          "track_condition": "稍",
          "frame": "1",
          "horse_number": "1",
          "weight": 55.0,
          "weight_reduction": "",
          "rank": "3",
          "margin": 0.4,
          "corrected_time": 88.0,
          "running_style": "中",
          "last_3f": 34.6,
          "ave_3f": 36.18,
          "pci": 54.6,
          "position_3f": 0.6
        },
        {
          "date": "2024.9.28",
          "race_name": "新馬・牝",
          "place": "中山",
          "surface": "芝",
          "distance": "1600",
          "track_condition": "良",
          "frame": "2",
          "horse_number": "4",
          "weight": 55.0,
          "weight_reduction": "",
          "rank": "2",
          "margin": 0.3,
          "corrected_time": 86.0,
          "running_style": "先",
          "last_3f": 35.5,
          "ave_3f": 36.48,
          "pci": 52.8,
          "position_3f": 0.4
        }
      ],
      "indices": {
        "mining_index": 53.21,
        "corrected_time_deviation": 47.27,
        "zi_deviation": 43.19,
        "base_score": 49.93,
        "jockey_coefficient": 0.99368,
        "similarity_coefficient": 1.00867,
        "stability_coefficient": 0.99362,
        "total_coefficient_score": 0.001,
        "final_score": 51.37
      }
    },
    {
      "frame": 6,
      "horse_number": 11,
      "horse_name": "ポタリング",
      "mark": "*",
      "jockey": {
        "name": "柴田裕一",
        "weight": 54.0,
        "weight_reduction": "△",
        "this_year": {
          "wins": 10,
          "win_rate": 3.2,
          "place_rate": 7.9,
          "show_rate": 12.3
        },
        "last_year": {
          "wins": 19,
          "win_rate": 5.9,
          "place_rate": 10.0,
          "show_rate": 14.6
        }
      },
      "trainer": {
        "affiliation": "(美)",
        "name": "武藤善則",
        "this_year": {
          "wins": 14,
          "win_rate": 6.3,
          "place_rate": 13.5,
          "show_rate": 19.8
        },
        "last_year": {
          "wins": 13,
          "win_rate": 4.8,
          "place_rate": 12.5,
          "show_rate": 18.8
        }
      },
      "interval": 3,
      "zi_index": 95.0,
      "time_mining": 109.0,
      "battle_mining": 67.7,
      "past_races": [
        {
          "date": "2025.10.18",
          "race_name": "１勝ｸﾗｽ",
          "place": "新潟",
          "surface": "芝",
          "distance": "1800",
          "track_condition": "良",
          "frame": "5",
          "horse_number": "10",
          "weight": 56.0,
          "weight_reduction": "",
          "rank": "13",
          "margin": 1.0,
          "corrected_time": 91.0,
          "running_style": "中",
          "last_3f": 34.1,
          "ave_3f": 36.25,
          "pci": 56.3,
          "position_3f": 0.8
        },
        {
          "date": "2025.7.20",
          "race_name": "未勝利",
          "place": "福島",
          "surface": "芝",
          "distance": "1800",
          "track_condition": "良",
          "frame": "8",
          "horse_number": "14",
          "weight": 57.0,
          "weight_reduction": "",
          "rank": "1",
          "margin": -0.3,
          "corrected_time": 91.0,
          "running_style": "先",
          "last_3f": 35.9,
          "ave_3f": 37.55,
          "pci": 54.6,
          "position_3f": 0.1
        },
        {
          "date": "2025.6.21",
          "race_name": "未勝利",
          "place": "東京",
          "surface": "芝",
          "distance": "1600",
          "track_condition": "良",
          "frame": "5",
          "horse_number": "9",
          "weight": 57.0,
          "weight_reduction": "",
          "rank": "5",
          "margin": 0.8,
          "corrected_time": 87.0,
          "running_style": "先",
          "last_3f": 35.7,
          "ave_3f": 34.92,
          "pci": 47.8,
          "position_3f": 0.2
        },
        {
          "date": "2025.6.1",
          "race_name": "未勝利",
          "place": "東京",
          "surface": "芝",
          "distance": "1600",
          "track_condition": "稍",
          "frame": "5",
          "horse_number": "8",
          "weight": 57.0,
          "weight_reduction": "",
          "rank": "4",
          "margin": 0.6,
          "corrected_time": 87.0,
          "running_style": "中",
          "last_3f": 34.5,
          "ave_3f": 36.48,
          "pci": 55.7,
          "position_3f": 0.7
        },
        {
          "date": "2025.4.20",
          "race_name": "未勝利",
          "place": "中山",
          "surface": "芝",
          "distance": "2000",
          "track_condition": "良",
          "frame": "2",
          "horse_number": "3",
          "weight": 57.0,
          "weight_reduction": "",
          "rank": "11",
          "margin": 1.1,
          "corrected_time": 81.0,
          "running_style": "中",
          "last_3f": 35.0,
          "ave_3f": 36.77,
          "pci": 55.1,
          "position_3f": 0.7
        }
      ],
      "indices": {
        "mining_index": 60.15,
        "corrected_time_deviation": 38.01,
        "zi_deviation": 46.78,
        "base_score": 51.5,
        "jockey_coefficient": 0.98936,
        "similarity_coefficient": 1.006,
        "stability_coefficient": 0.99562,
        "total_coefficient_score": -0.0,
        "final_score": 51.34
      }
    },
    {
      "frame": 2,
      "horse_number": 4,
      "horse_name": "クインズステラ",
      "mark": "*",
      "jockey": {
        "name": "永島まな",
        "weight": 54.0,
        "weight_reduction": "◇",
        "this_year": {
          "wins": 18,
          "win_rate": 4.4,
          "place_rate": 7.1,
          "show_rate": 11.8
        },
        "last_year": {
          "wins": 32,
          "win_rate": 4.5,
          "place_rate": 9.5,
          "show_rate": 13.7
        }
      },
      "trainer": {
        "affiliation": "(美)",
        "name": "池上昌和",
        "this_year": {
          "wins": 14,
          "win_rate": 7.4,
          "place_rate": 11.1,
          "show_rate": 18.0
        },
        "last_year": {
          "wins": 17,
          "win_rate": 7.8,
          "place_rate": 16.0,
          "show_rate": 23.7
        }
      },
      "interval": 28,
      "zi_index": 104.0,
      "time_mining": 109.76,
      "battle_mining": 46.1,
      "past_races": [
        {
          "date": "2025.4.27",
          "race_name": "１勝ｸﾗｽ・牝",
          "place": "福島",
          "surface": "芝",
          "distance": "1800",
          "track_condition": "良",
          "frame": "7",
          "horse_number": "14",
          "weight": 53.0,
          "weight_reduction": "▲",
          "rank": "5",
          "margin": 0.3,
          "corrected_time": 97.0,
          "running_style": "後",
          "last_3f": 35.7,
          "ave_3f": 36.15,
          "pci": 51.3,
          "position_3f": 1.3
        },
        {
          "date": "2025.4.20",
          "race_name": "１勝ｸﾗｽ",
          "place": "福島",
          "surface": "芝",
          "distance": "1800",
          "track_condition": "良",
          "frame": "6",
          "horse_number": "12",
          "weight": 53.0,
          "weight_reduction": "▲",
          "rank": "13",
          "margin": 1.1,
          "corrected_time": 90.0,
          "running_style": "後",
          "last_3f": 35.5,
          "ave_3f": 36.2,
          "pci": 52.0,
          "position_3f": 1.3
        },
        {
          "date": "2025.2.16",
          "race_name": "１勝ｸﾗｽ・牝",
          "place": "小倉",
          "surface": "芝",
          "distance": "1800",
          "track_condition": "良",
          "frame": "4",
          "horse_number": "8",
          "weight": 53.0,
          "weight_reduction": "▲",
          "rank": "6",
          "margin": 0.9,
          "corrected_time": 96.0,
          "running_style": "後",
          "last_3f": 35.4,
          "ave_3f": 36.35,
          "pci": 52.7,
          "position_3f": 1.7
        },
        {
          "date": "2025.2.1",
          "race_name": "１勝ｸﾗｽ・若",
          "place": "小倉",
          "surface": "芝",
          "distance": "1800",
          "track_condition": "稍",
          "frame": "5",
          "horse_number": "9",
          "weight": 53.0,
          "weight_reduction": "▲",
          "rank": "4",
          "margin": 0.6,
          "corrected_time": 97.0,
          "running_style": "中",
          "last_3f": 36.1,
          "ave_3f": 36.45,
          "pci": 51.0,
          "position_3f": 0.8
        },
        {
          "date": "2024.12.28",
          "race_name": "１勝ｸﾗｽ",
          "place": "中山",
          "surface": "芝",
          "distance": "1800",
          "track_condition": "良",
          "frame": "6",
          "horse_number": "12",
          "weight": 56.0,
          "weight_reduction": "",
          "rank": "10",
          "margin": 1.0,
          "corrected_time": 95.0,
          "running_style": "後",
          "last_3f": 35.4,
          "ave_3f": 36.75,
          "pci": 53.8,
          "position_3f": 1.3
        },
        {
          "date": "2024.8.10",
          "race_name": "石狩特別･1勝",
          "place": "札幌",
          "surface": "芝",
          "distance": "1800",
          "track_condition": "良",
          "frame": "4",
          "horse_number": "5",
          "weight": 56.0,
          "weight_reduction": "",
          "rank": "9",
          "margin": 0.7,
          "corrected_time": 93.0,
          "running_style": "中",
          "last_3f": 36.2,
          "ave_3f": 36.25,
          "pci": 50.1,
          "position_3f": 0.9
        },
        {
          "date": "2024.8.3",
          "race_name": "１勝ｸﾗｽ",
          "place": "札幌",
          "surface": "芝",
          "distance": "1800",
          "track_condition": "良",
          "frame": "6",
          "horse_number": "8",
          "weight": 53.0,
          "weight_reduction": "▲",
          "rank": "10",
          "margin": 1.4,
          "corrected_time": 93.0,
          "running_style": "後",
          "last_3f": 35.1,
          "ave_3f": 36.85,
          "pci": 55.0,
          "position_3f": 1.4
        },
        {
          "date": "2024.7.14",
          "race_name": "１勝ｸﾗｽ",
          "place": "福島",
          "surface": "芝",
          "distance": "1800",
          "track_condition": "良",
          "frame": "1",
          "horse_number": "1",
          "weight": 56.0,
          "weight_reduction": "",
          "rank": "11",
          "margin": 1.1,
          "corrected_time": 88.0,
          "running_style": "中",
          "last_3f": 36.2,
          "ave_3f": 36.65,
          "pci": 51.2,
          "position_3f": 0.8
        },
        {
          "date": "2024.4.20",
          "race_name": "１勝ｸﾗｽ・牝",
          "place": "福島",
          "surface": "芝",
          "distance": "1800",
          "track_condition": "良",
          "frame": "7",
          "horse_number": "9",
          "weight": 56.0,
          "weight_reduction": "",
          "rank": "5",
          "margin": 0.3,
          "corrected_time": 95.0,
          "running_style": "後",
          "last_3f": 34.7,
          "ave_3f": 36.9,
          "pci": 56.3,
          "position_3f": 1.4
        },
        {
          "date": "2024.4.13",
          "race_name": "１勝ｸﾗｽ",
          "place": "福島",
          "surface": "芝",
          "distance": "1800",
          "track_condition": "良",
          "frame": "4",
          "horse_number": "6",
          "weight": 56.0,
          "weight_reduction": "",
          "rank": "3",
          "margin": 0.1,
          "corrected_time": 97.0,
          "running_style": "先",
          "last_3f": 36.1,
          "ave_3f": 36.0,
          "pci": 49.7,
          "position_3f": 0.2
        }
      ],
      "indices": {
        "mining_index": 44.68,
        "corrected_time_deviation": 61.48,
        "zi_deviation": 57.56,
        "base_score": 51.65,
        "jockey_coefficient": 0.98874,
        "similarity_coefficient": 1.00547,
        "stability_coefficient": 0.9961,
        "total_coefficient_score": -0.0,
        "final_score": 51.24
      }
    },
    {
      "frame": 4,
      "horse_number": 8,
      "horse_name": "レッドイステル",
      "mark": "",
      "jockey": {
        "name": "西塚洸二",
        "weight": 55.0,
        "weight_reduction": "☆",
        "this_year": {
          "wins": 20,
          "win_rate": 6.2,
          "place_rate": 13.6,
          "show_rate": 17.6
        },
        "last_year": {
          "wins": 45,
          "win_rate": 7.8,
          "place_rate": 14.7,
          "show_rate": 20.9
        }
      },
      "trainer": {
        "affiliation": "(栗)",
        "name": "友道康夫",
        "this_year": {
          "wins": 35,
          "win_rate": 13.4,
          "place_rate": 26.4,
          "show_rate": 36.8
        },
        "last_year": {
          "wins": 53,
          "win_rate": 17.7,
          "place_rate": 31.3,
          "show_rate": 40.0
        }
      },
      "interval": 3,
      "zi_index": 112.0,
      "time_mining": 109.31,
      "battle_mining": 56.3,
      "past_races": [
        {
          "date": "2025.10.18",
          "race_name": "１勝ｸﾗｽ",
          "place": "新潟",
          "surface": "芝",
          "distance": "1800",
          "track_condition": "良",
          "frame": "4",
          "horse_number": "8",
          "weight": 55.0,
          "weight_reduction": "☆",
          "rank": "8",
          "margin": 0.8,
          "corrected_time": 93.0,
          "running_style": "先",
          "last_3f": 34.4,
          "ave_3f": 36.0,
          "pci": 54.7,
          "position_3f": 0.3
        },
        {
          "date": "2025.7.5",
          "race_name": "ロイヤル･1勝",
          "place": "小倉",
          "surface": "芝",
          "distance": "2000",
          "track_condition": "良",
          "frame": "3",
          "horse_number": "3",
          "weight": 55.0,
          "weight_reduction": "",
          "rank": "8",
          "margin": 2.8,
          "corrected_time": 75.0,
          "running_style": "先",
          "last_3f": 39.4,
          "ave_3f": 35.79,
          "pci": 40.8,
          "position_3f": 0.3
        },
        {
          "date": "2025.5.17",
          "race_name": "あずさ賞･1勝",
          "place": "京都",
          "surface": "芝",
          "distance": "2000",
          "track_condition": "不",
          "frame": "8",
          "horse_number": "9",
          "weight": 57.0,
          "weight_reduction": "",
          "rank": "8",
          "margin": 1.6,
          "corrected_time": 87.0,
          "running_style": "先",
          "last_3f": 37.1,
          "ave_3f": 36.56,
          "pci": 48.5,
          "position_3f": 0.2
        },
        {
          "date": "2025.4.5",
          "race_name": "未勝利",
          "place": "阪神",
          "surface": "芝",
          "distance": "1800",
          "track_condition": "良",
          "frame": "4",
          "horse_number": "8",
          "weight": 57.0,
          "weight_reduction": "",
          "rank": "1",
          "margin": -0.5,
          "corrected_time": 92.0,
          "running_style": "中",
          "last_3f": 34.2,
          "ave_3f": 36.05,
          "pci": 55.4,
          "position_3f": 0.5
        },
        {
          "date": "2025.3.15",
          "race_name": "未勝利",
          "place": "阪神",
          "surface": "芝",
          "distance": "1800",
          "track_condition": "良",
          "frame": "5",
          "horse_number": "9",
          "weight": 57.0,
          "weight_reduction": "",
          "rank": "2",
          "margin": 0.4,
          "corrected_time": 88.0,
          "running_style": "中",
          "last_3f": 33.9,
          "ave_3f": 37.05,
          "pci": 59.3,
          "position_3f": 0.7
        }
      ],
      "indices": {
        "mining_index": 52.55,
        "corrected_time_deviation": 36.77,
        "zi_deviation": 67.14,
        "base_score": 50.01,
        "jockey_coefficient": 0.99474,
        "similarity_coefficient": 1.00829,
        "stability_coefficient": 0.993,
        "total_coefficient_score": 0.001,
        "final_score": 51.14
      }
    },
    {
      "frame": 1,
      "horse_number": 1,
      "horse_name": "スピンザブラッド",
      "mark": "*",
      "jockey": {
        "name": "石神深道",
        "weight": 55.0,
        "weight_reduction": "▲",
        "this_year": {
          "wins": 14,
          "win_rate": 3.6,
          "place_rate": 7.6,
          "show_rate": 14.3
        },
        "last_year": {
          "wins": 4,
          "win_rate": 1.7,
          "place_rate": 2.9,
          "show_rate": 6.3
        }
      },
      "trainer": {
        "affiliation": "(美)",
        "name": "萩原清",
        "this_year": {
          "wins": 23,
          "win_rate": 15.6,
          "place_rate": 25.2,
          "show_rate": 31.3
        },
        "last_year": {
          "wins": 14,
          "win_rate": 8.1,
          "place_rate": 20.8,
          "show_rate": 32.4
        }
      },
      "interval": 14,
      "zi_index": 92.0,
      "time_mining": 109.14,
      "battle_mining": 45.9,
      "past_races": [
        {
          "date": "2025.8.2",
          "race_name": "１勝ｸﾗｽ",
          "place": "札幌",
          "surface": "芝",
          "distance": "1800",
          "track_condition": "良",
          "frame": "4",
          "horse_number": "4",
          "weight": 58.0,
          "weight_reduction": "",
          "rank": "9",
          "margin": 1.7,
          "corrected_time": 87.0,
          "running_style": "後",
          "last_3f": 34.5,
          "ave_3f": 36.9,
          "pci": 57.0,
          "position_3f": 2.1
        },
        {
          "date": "2025.6.22",
          "race_name": "１勝ｸﾗｽ",
          "place": "函館",
          "surface": "芝",
          "distance": "1800",
          "track_condition": "重",
          "frame": "4",
          "horse_number": "4",
          "weight": 58.0,
          "weight_reduction": "",
          "rank": "2",
          "margin": 0.0,
          "corrected_time": 99.0,
          "running_style": "後",
          "last_3f": 35.4,
          "ave_3f": 36.15,
          "pci": 52.1,
          "position_3f": 0.8
        },
        {
          "date": "2025.5.17",
          "race_name": "尖閣湾特･1勝",
          "place": "新潟",
          "surface": "芝",
          "distance": "2000",
          "track_condition": "稍",
          "frame": "8",
          "horse_number": "8",
          "weight": 58.0,
          "weight_reduction": "",
          "rank": "6",
          "margin": 0.6,
          "corrected_time": 95.0,
          "running_style": "先",
          "last_3f": 35.3,
          "ave_3f": 37.93,
          "pci": 57.4,
          "position_3f": 0.3
        },
        {
          "date": "2025.3.15",
          "race_name": "１勝ｸﾗｽ",
          "place": "中京",
          "surface": "芝",
          "distance": "2200",
          "track_condition": "良",
          "frame": "8",
          "horse_number": "16",
          "weight": 57.0,
          "weight_reduction": "",
          "rank": "6",
          "margin": 0.3,
          "corrected_time": 96.0,
          "running_style": "先",
          "last_3f": 35.3,
          "ave_3f": 37.54,
          "pci": 56.3,
          "position_3f": 0.2
        },
        {
          "date": "2024.10.31",
          "race_name": "シュウ",
          "place": "門別",
          "surface": "ダ",
          "distance": "1800",
          "track_condition": "良",
          "frame": "8",
          "horse_number": "11",
          "weight": 57.0,
          "weight_reduction": "",
          "rank": "1",
          "margin": -0.3,
          "corrected_time": 0.0,
          "running_style": "先",
          "last_3f": 0.0,
          "ave_3f": 0.0,
          "pci": 0.0,
          "position_3f": 0.0
        },
        {
          "date": "2024.10.24",
          "race_name": "３歳以",
          "place": "門別",
          "surface": "ダ",
          "distance": "1600",
          "track_condition": "重",
          "frame": "7",
          "horse_number": "7",
          "weight": 57.0,
          "weight_reduction": "",
          "rank": "1",
          "margin": -0.0,
          "corrected_time": 0.0,
          "running_style": "先",
          "last_3f": 0.0,
          "ave_3f": 0.0,
          "pci": 0.0,
          "position_3f": 0.0
        },
        {
          "date": "2024.10.10",
          "race_name": "３歳以",
          "place": "門別",
          "surface": "ダ",
          "distance": "1700",
          "track_condition": "良",
          "frame": "6",
          "horse_number": "7",
          "weight": 57.0,
          "weight_reduction": "",
          "rank": "2",
          "margin": 0.3,
          "corrected_time": 0.0,
          "running_style": "先",
          "last_3f": 0.0,
          "ave_3f": 0.0,
          "pci": 0.0,
          "position_3f": 0.0
        },
        {
          "date": "2024.9.12",
          "race_name": "３歳以",
          "place": "門別",
          "surface": "ダ",
          "distance": "1600",
          "track_condition": "良",
          "frame": "8",
          "horse_number": "10",
          "weight": 57.0,
          "weight_reduction": "",
          "rank": "1",
          "margin": -0.5,
          "corrected_time": 0.0,
          "running_style": "先",
          "last_3f": 0.0,
          "ave_3f": 0.0,
          "pci": 0.0,
          "position_3f": 0.0
        },
        {
          "date": "2024.8.11",
          "race_name": "未勝利",
          "place": "札幌",
          "surface": "ダ",
          "distance": "2400",
          "track_condition": "良",
          "frame": "1",
          "horse_number": "1",
          "weight": 57.0,
          "weight_reduction": "",
          "rank": "7",
          "margin": 2.5,
          "corrected_time": 64.0,
          "running_style": "中",
          "last_3f": 40.9,
          "ave_3f": 39.87,
          "pci": 47.5,
          "position_3f": 1.3
        },
        {
          "date": "2024.7.13",
          "race_name": "未勝利",
          "place": "函館",
          "surface": "ダ",
          "distance": "1700",
          "track_condition": "良",
          "frame": "1",
          "horse_number": "1",
          "weight": 57.0,
          "weight_reduction": "",
          "rank": "5",
          "margin": 2.8,
          "corrected_time": 73.0,
          "running_style": "後",
          "last_3f": 38.0,
          "ave_3f": 37.85,
          "pci": 49.6,
          "position_3f": 2.3
        }
      ],
      "indices": {
        "mining_index": 47.12,
        "corrected_time_deviation": 59.16,
        "zi_deviation": 43.19,
        "base_score": 50.14,
        "jockey_coefficient": 0.99162,
        "similarity_coefficient": 1.00446,
        "stability_coefficient": 0.99575,
        "total_coefficient_score": -0.001,
        "final_score": 49.5
      }
    },
    {
      "frame": 8,
      "horse_number": 15,
      "horse_name": "セザンワールド",
      "mark": "",
      "jockey": {
        "name": "小林脩斗",
        "weight": 58.0,
        "weight_reduction": "",
        "this_year": {
          "wins": 5,
          "win_rate": 2.6,
          "place_rate": 5.6,
          "show_rate": 10.2
        },
        "last_year": {
          "wins": 1,
          "win_rate": 0.6,
          "place_rate": 5.3,
          "show_rate": 10.5
        }
      },
      "trainer": {
        "affiliation": "(美)",
        "name": "蛯名利弘",
        "this_year": {
          "wins": 4,
          "win_rate": 2.1,
          "place_rate": 4.7,
          "show_rate": 8.3
        },
        "last_year": {
          "wins": 2,
          "win_rate": 0.9,
          "place_rate": 2.8,
          "show_rate": 4.7
        }
      },
      "interval": 2,
      "zi_index": 98.0,
      "time_mining": 109.58,
      "battle_mining": 42.6,
      "past_races": [
        {
          "date": "2025.10.25",
          "race_name": "１勝ｸﾗｽ・若",
          "place": "新潟",
          "surface": "芝",
          "distance": "1800",
          "track_condition": "良",
          "frame": "5",
          "horse_number": "8",
          "weight": 58.0,
          "weight_reduction": "",
          "rank": "9",
          "margin": 1.2,
          "corrected_time": 88.0,
          "running_style": "後",
          "last_3f": 34.3,
          "ave_3f": 36.75,
          "pci": 57.1,
          "position_3f": 0.7
        },
        {
          "date": "2025.9.20",
          "race_name": "１勝ｸﾗｽ",
          "place": "中山",
          "surface": "芝",
          "distance": "2000",
          "track_condition": "良",
          "frame": "2",
          "horse_number": "4",
          "weight": 55.0,
          "weight_reduction": "▲",
          "rank": "16",
          "margin": 1.7,
          "corrected_time": 83.0,
          "running_style": "後",
          "last_3f": 35.1,
          "ave_3f": 37.33,
          "pci": 56.3,
          "position_3f": 1.6
        },
        {
          "date": "2025.8.31",
          "race_name": "瓢湖特別･1勝",
          "place": "新潟",
          "surface": "芝",
          "distance": "2200",
          "track_condition": "良",
          "frame": "7",
          "horse_number": "10",
          "weight": 58.0,
          "weight_reduction": "",
          "rank": "6",
          "margin": 0.8,
          "corrected_time": 96.0,
          "running_style": "中",
          "last_3f": 35.9,
          "ave_3f": 36.94,
          "pci": 52.9,
          "position_3f": 0.4
        },
        {
          "date": "2025.7.6",
          "race_name": "１勝ｸﾗｽ",
          "place": "福島",
          "surface": "芝",
          "distance": "1800",
          "track_condition": "良",
          "frame": "3",
          "horse_number": "4",
          "weight": 58.0,
          "weight_reduction": "",
          "rank": "4",
          "margin": 0.4,
          "corrected_time": 98.0,
          "running_style": "中",
          "last_3f": 36.0,
          "ave_3f": 36.55,
          "pci": 51.5,
          "position_3f": 1.4
        },
        {
          "date": "2025.6.15",
          "race_name": "１勝ｸﾗｽ",
          "place": "東京",
          "surface": "ダ",
          "distance": "1600",
          "track_condition": "重",
          "frame": "7",
          "horse_number": "14",
          "weight": 58.0,
          "weight_reduction": "",
          "rank": "8",
          "margin": 0.8,
          "corrected_time": 93.0,
          "running_style": "中",
          "last_3f": 36.3,
          "ave_3f": 36.18,
          "pci": 49.7,
          "position_3f": 0.6
        },
        {
          "date": "2024.12.7",
          "race_name": "１勝ｸﾗｽ",
          "place": "中山",
          "surface": "ダ",
          "distance": "1800",
          "track_condition": "良",
          "frame": "7",
          "horse_number": "13",
          "weight": 56.0,
          "weight_reduction": "△",
          "rank": "6",
          "margin": 1.3,
          "corrected_time": 92.0,
          "running_style": "後",
          "last_3f": 38.1,
          "ave_3f": 38.5,
          "pci": 51.0,
          "position_3f": 1.0
        },
        {
          "date": "2024.11.17",
          "race_name": "１勝ｸﾗｽ",
          "place": "東京",
          "surface": "ダ",
          "distance": "2100",
          "track_condition": "良",
          "frame": "2",
          "horse_number": "3",
          "weight": 58.0,
          "weight_reduction": "",
          "rank": "11",
          "margin": 2.3,
          "corrected_time": 78.0,
          "running_style": "中",
          "last_3f": 39.0,
          "ave_3f": 37.68,
          "pci": 46.6,
          "position_3f": 1.0
        },
        {
          "date": "2024.9.27",
          "race_name": "デスマ",
          "place": "園田",
          "surface": "ダ",
          "distance": "1400",
          "track_condition": "良",
          "frame": "7",
          "horse_number": "10",
          "weight": 56.0,
          "weight_reduction": "",
          "rank": "2",
          "margin": 0.4,
          "corrected_time": 0.0,
          "running_style": "中",
          "last_3f": 0.0,
          "ave_3f": 0.0,
          "pci": 0.0,
          "position_3f": 0.0
        },
        {
          "date": "2024.9.6",
          "race_name": "そのだ",
          "place": "園田",
          "surface": "ダ",
          "distance": "1400",
          "track_condition": "良",
          "frame": "5",
          "horse_number": "5",
          "weight": 56.0,
          "weight_reduction": "",
          "rank": "2",
          "margin": 0.3,
          "corrected_time": 0.0,
          "running_style": "中",
          "last_3f": 0.0,
          "ave_3f": 0.0,
          "pci": 0.0,
          "position_3f": 0.0
        },
        {
          "date": "2024.8.21",
          "race_name": "Ｃ２一",
          "place": "園田",
          "surface": "ダ",
          "distance": "1400",
          "track_condition": "稍",
          "frame": "2",
          "horse_number": "2",
          "weight": 57.0,
          "weight_reduction": "",
          "rank": "2",
          "margin": 0.0,
          "corrected_time": 0.0,
          "running_style": "先",
          "last_3f": 0.0,
          "ave_3f": 0.0,
          "pci": 0.0,
          "position_3f": 0.0
        }
      ],
      "indices": {
        "mining_index": 44.06,
        "corrected_time_deviation": 50.98,
        "zi_deviation": 50.37,
        "base_score": 47.08,
        "jockey_coefficient": 0.98655,
        "similarity_coefficient": 1.00899,
        "stability_coefficient": 0.99401,
        "total_coefficient_score": 0.0,
        "final_score": 47.53
      }
    },
    {
      "frame": 1,
      "horse_number": 2,
      "horse_name": "ツインクルステージ",
      "mark": "*",
      "jockey": {
        "name": "泉谷楓真",
        "weight": 56.0,
        "weight_reduction": "",
        "this_year": {
          "wins": 5,
          "win_rate": 4.5,
          "place_rate": 6.4,
          "show_rate": 17.3
        },
        "last_year": {
          "wins": 3,
          "win_rate": 1.7,
          "place_rate": 6.1,
          "show_rate": 11.0
        }
      },
      "trainer": {
        "affiliation": "(美)",
        "name": "高木登",
        "this_year": {
          "wins": 22,
          "win_rate": 9.4,
          "place_rate": 16.3,
          "show_rate": 23.2
        },
        "last_year": {
          "wins": 26,
          "win_rate": 10.1,
          "place_rate": 18.7,
          "show_rate": 30.0
        }
      },
      "interval": 3,
      "zi_index": 94.0,
      "time_mining": 109.01,
      "battle_mining": 48.0,
      "past_races": [
        {
          "date": "2025.10.18",
          "race_name": "１勝ｸﾗｽ",
          "place": "新潟",
          "surface": "芝",
          "distance": "1800",
          "track_condition": "良",
          "frame": "6",
          "horse_number": "11",
          "weight": 53.0,
          "weight_reduction": "▲",
          "rank": "12",
          "margin": 0.9,
          "corrected_time": 92.0,
          "running_style": "先",
          "last_3f": 34.5,
          "ave_3f": 36.0,
          "pci": 54.3,
          "position_3f": 0.3
        },
        {
          "date": "2025.9.27",
          "race_name": "１勝ｸﾗｽ・牝",
          "place": "中山",
          "surface": "ダ",
          "distance": "1800",
          "track_condition": "良",
          "frame": "3",
          "horse_number": "5",
          "weight": 53.0,
          "weight_reduction": "▲",
          "rank": "15",
          "margin": 2.2,
          "corrected_time": 78.0,
          "running_style": "中",
          "last_3f": 39.5,
          "ave_3f": 38.75,
          "pci": 48.1,
          "position_3f": 0.5
        },
        {
          "date": "2025.9.6",
          "race_name": "１勝ｸﾗｽ・牝",
          "place": "中山",
          "surface": "ダ",
          "distance": "1800",
          "track_condition": "稍",
          "frame": "6",
          "horse_number": "6",
          "weight": 53.0,
          "weight_reduction": "▲",
          "rank": "3",
          "margin": 1.3,
          "corrected_time": 92.0,
          "running_style": "先",
          "last_3f": 38.3,
          "ave_3f": 38.05,
          "pci": 49.3,
          "position_3f": 0.1
        },
        {
          "date": "2025.6.1",
          "race_name": "１勝ｸﾗｽ",
          "place": "東京",
          "surface": "芝",
          "distance": "1800",
          "track_condition": "稍",
          "frame": "1",
          "horse_number": "1",
          "weight": 53.0,
          "weight_reduction": "▲",
          "rank": "7",
          "margin": 1.1,
          "corrected_time": 95.0,
          "running_style": "逃",
          "last_3f": 35.2,
          "ave_3f": 35.85,
          "pci": 51.8,
          "position_3f": 0.0
        },
        {
          "date": "2025.5.11",
          "race_name": "１勝ｸﾗｽ",
          "place": "新潟",
          "surface": "芝",
          "distance": "1800",
          "track_condition": "稍",
          "frame": "3",
          "horse_number": "3",
          "weight": 53.0,
          "weight_reduction": "▲",
          "rank": "7",
          "margin": 0.6,
          "corrected_time": 94.0,
          "running_style": "先",
          "last_3f": 36.0,
          "ave_3f": 36.95,
          "pci": 52.6,
          "position_3f": 0.2
        },
        {
          "date": "2025.4.27",
          "race_name": "１勝ｸﾗｽ・牝",
          "place": "福島",
          "surface": "芝",
          "distance": "1800",
          "track_condition": "良",
          "frame": "1",
          "horse_number": "1",
          "weight": 56.0,
          "weight_reduction": "",
          "rank": "9",
          "margin": 0.8,
          "corrected_time": 92.0,
          "running_style": "中",
          "last_3f": 36.1,
          "ave_3f": 36.2,
          "pci": 50.3,
          "position_3f": 1.4
        },
        {
          "date": "2025.1.18",
          "race_name": "１勝ｸﾗｽ",
          "place": "中山",
          "surface": "芝",
          "distance": "2000",
          "track_condition": "良",
          "frame": "3",
          "horse_number": "5",
          "weight": 55.0,
          "weight_reduction": "",
          "rank": "7",
          "margin": 1.3,
          "corrected_time": 94.0,
          "running_style": "先",
          "last_3f": 36.2,
          "ave_3f": 36.3,
          "pci": 50.3,
          "position_3f": 0.6
        },
        {
          "date": "2024.10.26",
          "race_name": "１勝ｸﾗｽ",
          "place": "東京",
          "surface": "芝",
          "distance": "2000",
          "track_condition": "良",
          "frame": "4",
          "horse_number": "4",
          "weight": 54.0,
          "weight_reduction": "",
          "rank": "8",
          "margin": 1.6,
          "corrected_time": 87.0,
          "running_style": "中",
          "last_3f": 35.0,
          "ave_3f": 36.51,
          "pci": 54.3,
          "position_3f": 0.8
        },
        {
          "date": "2024.7.7",
          "race_name": "未勝利・牝",
          "place": "福島",
          "surface": "芝",
          "distance": "1800",
          "track_condition": "良",
          "frame": "7",
          "horse_number": "13",
          "weight": 55.0,
          "weight_reduction": "",
          "rank": "1",
          "margin": -0.0,
          "corrected_time": 87.0,
          "running_style": "中",
          "last_3f": 36.6,
          "ave_3f": 36.1,
          "pci": 48.6,
          "position_3f": 0.4
        },
        {
          "date": "2024.6.15",
          "race_name": "未勝利・牝",
          "place": "東京",
          "surface": "ダ",
          "distance": "1600",
          "track_condition": "良",
          "frame": "6",
          "horse_number": "12",
          "weight": 55.0,
          "weight_reduction": "",
          "rank": "5",
          "margin": 1.4,
          "corrected_time": 80.0,
          "running_style": "中",
          "last_3f": 37.9,
          "ave_3f": 36.78,
          "pci": 47.0,
          "position_3f": 0.6
        }
      ],
      "indices": {
        "mining_index": 48.77,
        "corrected_time_deviation": 46.65,
        "zi_deviation": 45.58,
        "base_score": 47.65,
        "jockey_coefficient": 0.99448,
        "similarity_coefficient": 1.00581,
        "stability_coefficient": 0.99313,
        "total_coefficient_score": -0.0,
        "final_score": 47.27
      }
    },
    {
      "frame": 3,
      "horse_number": 5,
      "horse_name": "フラッシングレート",
      "mark": "*",
      "jockey": {
        "name": "亀田温心",
        "weight": 56.0,
        "weight_reduction": "",
        "this_year": {
          "wins": 14,
          "win_rate": 6.5,
          "place_rate": 11.1,
          "show_rate": 15.7
        },
        "last_year": {
          "wins": 17,
          "win_rate": 5.5,
          "place_rate": 12.3,
          "show_rate": 17.5
        }
      },
      "trainer": {
        "affiliation": "(栗)",
        "name": "加藤公太",
        "this_year": {
          "wins": 7,
          "win_rate": 5.5,
          "place_rate": 9.4,
          "show_rate": 16.4
        },
        "last_year": {
          "wins": 0,
          "win_rate": 0.0,
          "place_rate": 0.0,
          "show_rate": 0.0
        }
      },
      "interval": 11,
      "zi_index": 89.0,
      "time_mining": 109.03,
      "battle_mining": 48.0,
      "past_races": [
        {
          "date": "2025.8.23",
          "race_name": "１勝ｸﾗｽ・牝",
          "place": "札幌",
          "surface": "芝",
          "distance": "1800",
          "track_condition": "稍",
          "frame": "4",
          "horse_number": "6",
          "weight": 54.0,
          "weight_reduction": "△",
          "rank": "12",
          "margin": 1.7,
          "corrected_time": 86.0,
          "running_style": "中",
          "last_3f": 36.6,
          "ave_3f": 37.35,
          "pci": 52.0,
          "position_3f": 0.9
        },
        {
          "date": "2025.8.3",
          "race_name": "１勝ｸﾗｽ・牝",
          "place": "札幌",
          "surface": "芝",
          "distance": "2000",
          "track_condition": "良",
          "frame": "8",
          "horse_number": "10",
          "weight": 53.0,
          "weight_reduction": "▲",
          "rank": "9",
          "margin": 1.1,
          "corrected_time": 92.0,
          "running_style": "中",
          "last_3f": 36.2,
          "ave_3f": 36.56,
          "pci": 51.0,
          "position_3f": 0.5
        },
        {
          "date": "2025.7.13",
          "race_name": "１勝ｸﾗｽ・牝",
          "place": "函館",
          "surface": "芝",
          "distance": "1800",
          "track_condition": "良",
          "frame": "8",
          "horse_number": "13",
          "weight": 56.0,
          "weight_reduction": "",
          "rank": "9",
          "margin": 0.7,
          "corrected_time": 95.0,
          "running_style": "中",
          "last_3f": 34.8,
          "ave_3f": 36.25,
          "pci": 54.2,
          "position_3f": 1.7
        },
        {
          "date": "2025.4.27",
          "race_name": "１勝ｸﾗｽ・牝",
          "place": "福島",
          "surface": "芝",
          "distance": "1800",
          "track_condition": "良",
          "frame": "8",
          "horse_number": "16",
          "weight": 56.0,
          "weight_reduction": "",
          "rank": "11",
          "margin": 1.2,
          "corrected_time": 88.0,
          "running_style": "先",
          "last_3f": 37.1,
          "ave_3f": 35.9,
          "pci": 46.8,
          "position_3f": 0.8
        },
        {
          "date": "2025.3.29",
          "race_name": "１勝ｸﾗｽ・牝",
          "place": "中京",
          "surface": "芝",
          "distance": "2000",
          "track_condition": "重",
          "frame": "3",
          "horse_number": "5",
          "weight": 56.0,
          "weight_reduction": "",
          "rank": "7",
          "margin": 1.1,
          "corrected_time": 93.0,
          "running_style": "中",
          "last_3f": 37.2,
          "ave_3f": 36.21,
          "pci": 47.4,
          "position_3f": 0.7
        },
        {
          "date": "2024.12.15",
          "race_name": "１勝ｸﾗｽ・牝",
          "place": "中京",
          "surface": "芝",
          "distance": "1600",
          "track_condition": "良",
          "frame": "8",
          "horse_number": "15",
          "weight": 56.0,
          "weight_reduction": "",
          "rank": "6",
          "margin": 0.5,
          "corrected_time": 96.0,
          "running_style": "後",
          "last_3f": 35.3,
          "ave_3f": 35.64,
          "pci": 51.0,
          "position_3f": 1.6
        },
        {
          "date": "2024.10.6",
          "race_name": "１勝ｸﾗｽ",
          "place": "京都",
          "surface": "芝",
          "distance": "1800",
          "track_condition": "良",
          "frame": "8",
          "horse_number": "15",
          "weight": 53.0,
          "weight_reduction": "▲",
          "rank": "4",
          "margin": 0.4,
          "corrected_time": 97.0,
          "running_style": "先",
          "last_3f": 34.7,
          "ave_3f": 35.85,
          "pci": 53.3,
          "position_3f": 0.3
        },
        {
          "date": "2024.9.8",
          "race_name": "１勝ｸﾗｽ",
          "place": "中京",
          "surface": "芝",
          "distance": "2000",
          "track_condition": "良",
          "frame": "1",
          "horse_number": "1",
          "weight": 53.0,
          "weight_reduction": "▲",
          "rank": "3",
          "margin": 0.2,
          "corrected_time": 99.0,
          "running_style": "先",
          "last_3f": 35.1,
          "ave_3f": 36.39,
          "pci": 53.7,
          "position_3f": 1.6
        },
        {
          "date": "2024.7.6",
          "race_name": "１勝ｸﾗｽ・牝",
          "place": "小倉",
          "surface": "芝",
          "distance": "1800",
          "track_condition": "良",
          "frame": "2",
          "horse_number": "4",
          "weight": 53.0,
          "weight_reduction": "▲",
          "rank": "11",
          "margin": 1.3,
          "corrected_time": 87.0,
          "running_style": "マ",
          "last_3f": 37.1,
          "ave_3f": 35.1,
          "pci": 44.6,
          "position_3f": 0.4
        },
        {
          "date": "2024.4.20",
          "race_name": "１勝ｸﾗｽ・牝",
          "place": "福島",
          "surface": "芝",
          "distance": "1800",
          "track_condition": "良",
          "frame": "6",
          "horse_number": "7",
          "weight": 56.0,
          "weight_reduction": "",
          "rank": "6",
          "margin": 0.3,
          "corrected_time": 95.0,
          "running_style": "先",
          "last_3f": 35.4,
          "ave_3f": 36.55,
          "pci": 53.2,
          "position_3f": 0.7
        }
      ],
      "indices": {
        "mining_index": 48.75,
        "corrected_time_deviation": 48.51,
        "zi_deviation": 39.6,
        "base_score": 47.3,
        "jockey_coefficient": 0.99302,
        "similarity_coefficient": 1.00681,
        "stability_coefficient": 0.99289,
        "total_coefficient_score": -0.0,
        "final_score": 47.15
      }
    },
    {
      "frame": 4,
      "horse_number": 7,
      "horse_name": "バセリーナ",
      "mark": "*",
      "jockey": {
        "name": "舟山瑠泉",
        "weight": 53.0,
        "weight_reduction": "▲",
        "this_year": {
          "wins": 14,
          "win_rate": 5.2,
          "place_rate": 12.3,
          "show_rate": 19.3
        },
        "last_year": {
          "wins": 0,
          "win_rate": 0.0,
          "place_rate": 0.0,
          "show_rate": 0.0
        }
      },
      "trainer": {
        "affiliation": "(美)",
        "name": "松山将樹",
        "this_year": {
          "wins": 8,
          "win_rate": 4.1,
          "place_rate": 8.2,
          "show_rate": 12.3
        },
        "last_year": {
          "wins": 8,
          "win_rate": 3.3,
          "place_rate": 6.7,
          "show_rate": 10.5
        }
      },
      "interval": 19,
      "zi_index": 95.0,
      "time_mining": 108.97,
      "battle_mining": 48.0,
      "past_races": [
        {
          "date": "2025.6.29",
          "race_name": "１勝ｸﾗｽ",
          "place": "福島",
          "surface": "芝",
          "distance": "1800",
          "track_condition": "良",
          "frame": "7",
          "horse_number": "7",
          "weight": 52.0,
          "weight_reduction": "▲",
          "rank": "6",
          "margin": 0.8,
          "corrected_time": 91.0,
          "running_style": "中",
          "last_3f": 34.6,
          "ave_3f": 37.25,
          "pci": 57.7,
          "position_3f": 1.1
        },
        {
          "date": "2025.6.8",
          "race_name": "１勝ｸﾗｽ",
          "place": "東京",
          "surface": "芝",
          "distance": "1600",
          "track_condition": "良",
          "frame": "5",
          "horse_number": "10",
          "weight": 55.0,
          "weight_reduction": "",
          "rank": "16",
          "margin": 1.6,
          "corrected_time": 84.0,
          "running_style": "後",
          "last_3f": 34.6,
          "ave_3f": 36.3,
          "pci": 54.9,
          "position_3f": 1.9
        },
        {
          "date": "2025.5.18",
          "race_name": "１勝ｸﾗｽ*",
          "place": "東京",
          "surface": "芝",
          "distance": "1600",
          "track_condition": "良",
          "frame": "8",
          "horse_number": "10",
          "weight": 57.0,
          "weight_reduction": "",
          "rank": "4",
          "margin": 1.2,
          "corrected_time": 92.0,
          "running_style": "後",
          "last_3f": 34.7,
          "ave_3f": 35.82,
          "pci": 53.2,
          "position_3f": 1.1
        },
        {
          "date": "2025.1.26",
          "race_name": "若竹賞･1勝*",
          "place": "中山",
          "surface": "芝",
          "distance": "1800",
          "track_condition": "良",
          "frame": "7",
          "horse_number": "8",
          "weight": 57.0,
          "weight_reduction": "",
          "rank": "10",
          "margin": 1.0,
          "corrected_time": 91.0,
          "running_style": "中",
          "last_3f": 36.7,
          "ave_3f": 36.9,
          "pci": 50.5,
          "position_3f": 0.8
        },
        {
          "date": "2025.1.5",
          "race_name": "ジュニア(L)",
          "place": "中山",
          "surface": "芝",
          "distance": "1600",
          "track_condition": "良",
          "frame": "7",
          "horse_number": "13",
          "weight": 57.0,
          "weight_reduction": "",
          "rank": "9",
          "margin": 1.2,
          "corrected_time": 96.0,
          "running_style": "後",
          "last_3f": 34.5,
          "ave_3f": 36.12,
          "pci": 54.7,
          "position_3f": 1.1
        },
        {
          "date": "2024.12.14",
          "race_name": "ひいらぎ･1勝",
          "place": "中山",
          "surface": "芝",
          "distance": "1600",
          "track_condition": "良",
          "frame": "8",
          "horse_number": "12",
          "weight": 56.0,
          "weight_reduction": "",
          "rank": "9",
          "margin": 1.5,
          "corrected_time": 89.0,
          "running_style": "後",
          "last_3f": 35.7,
          "ave_3f": 34.92,
          "pci": 47.8,
          "position_3f": 0.9
        },
        {
          "date": "2024.8.31",
          "race_name": "札幌２歳G3",
          "place": "札幌",
          "surface": "芝",
          "distance": "1800",
          "track_condition": "重",
          "frame": "6",
          "horse_number": "7",
          "weight": 55.0,
          "weight_reduction": "",
          "rank": "12",
          "margin": 3.7,
          "corrected_time": 65.0,
          "running_style": "中",
          "last_3f": 40.6,
          "ave_3f": 36.7,
          "pci": 40.4,
          "position_3f": 0.3
        },
        {
          "date": "2024.8.18",
          "race_name": "クローバ",
          "place": "札幌",
          "surface": "芝",
          "distance": "1500",
          "track_condition": "良",
          "frame": "2",
          "horse_number": "2",
          "weight": 55.0,
          "weight_reduction": "",
          "rank": "3",
          "margin": 0.7,
          "corrected_time": 90.0,
          "running_style": "先",
          "last_3f": 35.3,
          "ave_3f": 36.0,
          "pci": 52.0,
          "position_3f": 0.3
        },
        {
          "date": "2024.7.6",
          "race_name": "未勝利*",
          "place": "福島",
          "surface": "芝",
          "distance": "1800",
          "track_condition": "良",
          "frame": "4",
          "horse_number": "4",
          "weight": 55.0,
          "weight_reduction": "",
          "rank": "1",
          "margin": -0.1,
          "corrected_time": 90.0,
          "running_style": "先",
          "last_3f": 35.0,
          "ave_3f": 38.1,
          "pci": 58.9,
          "position_3f": 0.4
        },
        {
          "date": "2024.6.23",
          "race_name": "未勝利*",
          "place": "東京",
          "surface": "芝",
          "distance": "1600",
          "track_condition": "稍",
          "frame": "6",
          "horse_number": "6",
          "weight": 55.0,
          "weight_reduction": "",
          "rank": "10",
          "margin": 1.8,
          "corrected_time": 71.0,
          "running_style": "後",
          "last_3f": 36.6,
          "ave_3f": 36.6,
          "pci": 50.0,
          "position_3f": 2.4
        }
      ],
      "indices": {
        "mining_index": 48.8,
        "corrected_time_deviation": 48.51,
        "zi_deviation": 46.78,
        "base_score": 48.41,
        "jockey_coefficient": 0.99612,
        "similarity_coefficient": 1.00267,
        "stability_coefficient": 0.99276,
        "total_coefficient_score": -0.002,
        "final_score": 46.25
      }
    },
    {
      "frame": 7,
      "horse_number": 14,
      "horse_name": "ニシノコマチムスメ",
      "mark": "*",
      "jockey": {
        "name": "今村聖奈",
        "weight": 54.0,
        "weight_reduction": "◇",
        "this_year": {
          "wins": 18,
          "win_rate": 6.2,
          "place_rate": 11.4,
          "show_rate": 16.3
        },
        "last_year": {
          "wins": 6,
          "win_rate": 3.1,
          "place_rate": 7.8,
          "show_rate": 12.5
        }
      },
      "trainer": {
        "affiliation": "(美)",
        "name": "松山将樹",
        "this_year": {
          "wins": 8,
          "win_rate": 4.1,
          "place_rate": 8.2,
          "show_rate": 12.3
        },
        "last_year": {
          "wins": 8,
          "win_rate": 3.3,
          "place_rate": 6.7,
          "show_rate": 10.5
        }
      },
      "interval": 9,
      "zi_index": 91.0,
      "time_mining": 109.54,
      "battle_mining": 46.8,
      "past_races": [
        {
          "date": "2025.9.6",
          "race_name": "古作特別･1勝",
          "place": "中山",
          "surface": "芝",
          "distance": "1800",
          "track_condition": "良",
          "frame": "3",
          "horse_number": "3",
          "weight": 56.0,
          "weight_reduction": "",
          "rank": "6",
          "margin": 0.5,
          "corrected_time": 94.0,
          "running_style": "中",
          "last_3f": 33.3,
          "ave_3f": 37.3,
          "pci": 62.0,
          "position_3f": 1.1
        },
        {
          "date": "2025.8.16",
          "race_name": "中郷特別･1勝",
          "place": "新潟",
          "surface": "芝",
          "distance": "1800",
          "track_condition": "良",
          "frame": "8",
          "horse_number": "12",
          "weight": 56.0,
          "weight_reduction": "",
          "rank": "10",
          "margin": 2.5,
          "corrected_time": 86.0,
          "running_style": "後",
          "last_3f": 34.5,
          "ave_3f": 36.4,
          "pci": 55.5,
          "position_3f": 1.5
        },
        {
          "date": "2025.7.13",
          "race_name": "織姫賞･1勝",
          "place": "福島",
          "surface": "芝",
          "distance": "1800",
          "track_condition": "良",
          "frame": "4",
          "horse_number": "4",
          "weight": 56.0,
          "weight_reduction": "",
          "rank": "9",
          "margin": 1.2,
          "corrected_time": 88.0,
          "running_style": "中",
          "last_3f": 36.3,
          "ave_3f": 36.8,
          "pci": 51.4,
          "position_3f": 1.0
        },
        {
          "date": "2025.5.18",
          "race_name": "１勝ｸﾗｽ・若",
          "place": "新潟",
          "surface": "芝",
          "distance": "1800",
          "track_condition": "良",
          "frame": "5",
          "horse_number": "6",
          "weight": 54.0,
          "weight_reduction": "◇",
          "rank": "8",
          "margin": 0.9,
          "corrected_time": 90.0,
          "running_style": "後",
          "last_3f": 35.5,
          "ave_3f": 37.15,
          "pci": 54.6,
          "position_3f": 0.6
        },
        {
          "date": "2025.4.27",
          "race_name": "１勝ｸﾗｽ・牝",
          "place": "福島",
          "surface": "芝",
          "distance": "1800",
          "track_condition": "良",
          "frame": "4",
          "horse_number": "7",
          "weight": 53.0,
          "weight_reduction": "▲",
          "rank": "4",
          "margin": 0.1,
          "corrected_time": 99.0,
          "running_style": "後",
          "last_3f": 35.3,
          "ave_3f": 36.25,
          "pci": 52.7,
          "position_3f": 1.5
        },
        {
          "date": "2025.3.1",
          "race_name": "１勝ｸﾗｽ・牝",
          "place": "小倉",
          "surface": "芝",
          "distance": "1800",
          "track_condition": "良",
          "frame": "6",
          "horse_number": "11",
          "weight": 56.0,
          "weight_reduction": "",
          "rank": "8",
          "margin": 1.0,
          "corrected_time": 93.0,
          "running_style": "中",
          "last_3f": 37.3,
          "ave_3f": 36.3,
          "pci": 47.3,
          "position_3f": 0.4
        },
        {
          "date": "2025.2.16",
          "race_name": "１勝ｸﾗｽ・牝",
          "place": "小倉",
          "surface": "芝",
          "distance": "1800",
          "track_condition": "良",
          "frame": "8",
          "horse_number": "16",
          "weight": 55.0,
          "weight_reduction": "",
          "rank": "5",
          "margin": 0.8,
          "corrected_time": 97.0,
          "running_style": "中",
          "last_3f": 35.7,
          "ave_3f": 36.15,
          "pci": 51.3,
          "position_3f": 1.3
        },
        {
          "date": "2025.1.25",
          "race_name": "１勝ｸﾗｽ",
          "place": "小倉",
          "surface": "芝",
          "distance": "1800",
          "track_condition": "良",
          "frame": "5",
          "horse_number": "10",
          "weight": 55.0,
          "weight_reduction": "",
          "rank": "9",
          "margin": 0.9,
          "corrected_time": 92.0,
          "running_style": "後",
          "last_3f": 34.4,
          "ave_3f": 37.0,
          "pci": 57.6,
          "position_3f": 1.8
        },
        {
          "date": "2024.11.16",
          "race_name": "１勝ｸﾗｽ",
          "place": "東京",
          "surface": "芝",
          "distance": "1600",
          "track_condition": "良",
          "frame": "7",
          "horse_number": "13",
          "weight": 55.0,
          "weight_reduction": "",
          "rank": "17",
          "margin": 1.8,
          "corrected_time": 82.0,
          "running_style": "中",
          "last_3f": 35.5,
          "ave_3f": 36.24,
          "pci": 52.1,
          "position_3f": 0.5
        },
        {
          "date": "2024.10.14",
          "race_name": "１勝ｸﾗｽ",
          "place": "東京",
          "surface": "芝",
          "distance": "1600",
          "track_condition": "良",
          "frame": "3",
          "horse_number": "6",
          "weight": 54.0,
          "weight_reduction": "",
          "rank": "8",
          "margin": 0.7,
          "corrected_time": 95.0,
          "running_style": "中",
          "last_3f": 35.1,
          "ave_3f": 34.98,
          "pci": 49.7,
          "position_3f": 0.8
        }
      ],
      "indices": {
        "mining_index": 46.4,
        "corrected_time_deviation": 50.36,
        "zi_deviation": 41.99,
        "base_score": 46.93,
        "jockey_coefficient": 0.99358,
        "similarity_coefficient": 1.00146,
        "stability_coefficient": 0.99463,
        "total_coefficient_score": -0.002,
        "final_score": 44.45
      }
    },
    {
      "frame": 5,
      "horse_number": 10,
      "horse_name": "レインオンミー",
      "mark": "",
      "jockey": {
        "name": "大久保友",
        "weight": 53.0,
        "weight_reduction": "▲",
        "this_year": {
          "wins": 0,
          "win_rate": 0.0,
          "place_rate": 0.0,
          "show_rate": 8.3
        },
        "last_year": {
          "wins": 0,
          "win_rate": 0.0,
          "place_rate": 0.0,
          "show_rate": 0.0
        }
      },
      "trainer": {
        "affiliation": "(栗)",
        "name": "福永祐一",
        "this_year": {
          "wins": 24,
          "win_rate": 12.4,
          "place_rate": 19.7,
          "show_rate": 32.6
        },
        "last_year": {
          "wins": 17,
          "win_rate": 11.2,
          "place_rate": 23.7,
          "show_rate": 35.5
        }
      },
      "interval": 2,
      "zi_index": 100.0,
      "time_mining": 109.32,
      "battle_mining": 55.7,
      "past_races": [
        {
          "date": "2025.10.25",
          "race_name": "１勝ｸﾗｽ・若",
          "place": "新潟",
          "surface": "芝",
          "distance": "1800",
          "track_condition": "良",
          "frame": "1",
          "horse_number": "1",
          "weight": 53.0,
          "weight_reduction": "▲",
          "rank": "7",
          "margin": 0.8,
          "corrected_time": 92.0,
          "running_style": "先",
          "last_3f": 34.3,
          "ave_3f": 36.55,
          "pci": 56.6,
          "position_3f": 0.3
        },
        {
          "date": "2025.8.10",
          "race_name": "１勝ｸﾗｽ",
          "place": "新潟",
          "surface": "芝",
          "distance": "2000",
          "track_condition": "重",
          "frame": "1",
          "horse_number": "1",
          "weight": 53.0,
          "weight_reduction": "◇",
          "rank": "11",
          "margin": 1.7,
          "corrected_time": 81.0,
          "running_style": "後",
          "last_3f": 34.5,
          "ave_3f": 38.7,
          "pci": 62.2,
          "position_3f": 1.9
        },
        {
          "date": "2025.7.19",
          "race_name": "未勝利",
          "place": "小倉",
          "surface": "芝",
          "distance": "1800",
          "track_condition": "稍",
          "frame": "7",
          "horse_number": "13",
          "weight": 57.0,
          "weight_reduction": "",
          "rank": "1",
          "margin": -0.1,
          "corrected_time": 87.0,
          "running_style": "中",
          "last_3f": 35.9,
          "ave_3f": 37.5,
          "pci": 54.5,
          "position_3f": 0.5
        },
        {
          "date": "2025.6.1",
          "race_name": "未勝利",
          "place": "京都",
          "surface": "芝",
          "distance": "1600",
          "track_condition": "良",
          "frame": "2",
          "horse_number": "4",
          "weight": 57.0,
          "weight_reduction": "",
          "rank": "10",
          "margin": 1.2,
          "corrected_time": 79.0,
          "running_style": "先",
          "last_3f": 36.8,
          "ave_3f": 35.34,
          "pci": 46.0,
          "position_3f": 0.2
        },
        {
          "date": "2025.5.10",
          "race_name": "未勝利",
          "place": "京都",
          "surface": "芝",
          "distance": "1400",
          "track_condition": "稍",
          "frame": "5",
          "horse_number": "9",
          "weight": 57.0,
          "weight_reduction": "",
          "rank": "7",
          "margin": 1.2,
          "corrected_time": 80.0,
          "running_style": "中",
          "last_3f": 35.6,
          "ave_3f": 35.55,
          "pci": 49.9,
          "position_3f": 1.3
        },
        {
          "date": "2025.3.15",
          "race_name": "未勝利",
          "place": "阪神",
          "surface": "芝",
          "distance": "1400",
          "track_condition": "良",
          "frame": "2",
          "horse_number": "3",
          "weight": 55.0,
          "weight_reduction": "△",
          "rank": "6",
          "margin": 0.8,
          "corrected_time": 82.0,
          "running_style": "中",
          "last_3f": 35.4,
          "ave_3f": 35.33,
          "pci": 49.8,
          "position_3f": 0.7
        },
        {
          "date": "2024.12.15",
          "race_name": "未勝利*",
          "place": "京都",
          "surface": "ダ",
          "distance": "1800",
          "track_condition": "良",
          "frame": "5",
          "horse_number": "7",
          "weight": 56.0,
          "weight_reduction": "",
          "rank": "14",
          "margin": 4.0,
          "corrected_time": 55.0,
          "running_style": "先",
          "last_3f": 41.4,
          "ave_3f": 38.85,
          "pci": 43.8,
          "position_3f": 0.3
        },
        {
          "date": "2024.11.30",
          "race_name": "未勝利*",
          "place": "京都",
          "surface": "ダ",
          "distance": "1400",
          "track_condition": "稍",
          "frame": "3",
          "horse_number": "3",
          "weight": 56.0,
          "weight_reduction": "",
          "rank": "13",
          "margin": 2.8,
          "corrected_time": 66.0,
          "running_style": "後",
          "last_3f": 38.6,
          "ave_3f": 38.1,
          "pci": 48.7,
          "position_3f": 1.9
        },
        {
          "date": "2024.9.14",
          "race_name": "新馬",
          "place": "中京",
          "surface": "芝",
          "distance": "1400",
          "track_condition": "良",
          "frame": "3",
          "horse_number": "3",
          "weight": 55.0,
          "weight_reduction": "",
          "rank": "6",
          "margin": 0.4,
          "corrected_time": 85.0,
          "running_style": "後",
          "last_3f": 33.9,
          "ave_3f": 36.53,
          "pci": 57.7,
          "position_3f": 0.8
        }
      ],
      "indices": {
        "mining_index": 52.19,
        "corrected_time_deviation": 26.89,
        "zi_deviation": 52.77,
        "base_score": 44.69,
        "jockey_coefficient": 0.98346,
        "similarity_coefficient": 1.00746,
        "stability_coefficient": 0.99268,
        "total_coefficient_score": -0.001,
        "final_score": 43.22
      }
    },
    {
      "frame": 7,
      "horse_number": 13,
      "horse_name": "チャイボーグ",
      "mark": "",
      "jockey": {
        "name": "橋木太希",
        "weight": 53.0,
        "weight_reduction": "▲",
        "this_year": {
          "wins": 1,
          "win_rate": 0.6,
          "place_rate": 2.5,
          "show_rate": 6.8
        },
        "last_year": {
          "wins": 1,
          "win_rate": 0.9,
          "place_rate": 6.1,
          "show_rate": 10.4
        }
      },
      "trainer": {
        "affiliation": "(美)",
        "name": "的場均",
        "this_year": {
          "wins": 1,
          "win_rate": 0.7,
          "place_rate": 0.7,
          "show_rate": 1.4
        },
        "last_year": {
          "wins": 2,
          "win_rate": 1.1,
          "place_rate": 1.1,
          "show_rate": 2.3
        }
      },
      "interval": 2,
      "zi_index": 92.0,
      "time_mining": 109.33,
      "battle_mining": 27.5,
      "past_races": [
        {
          "date": "2025.10.25",
          "race_name": "１勝ｸﾗｽ・若",
          "place": "新潟",
          "surface": "芝",
          "distance": "1800",
          "track_condition": "良",
          "frame": "2",
          "horse_number": "3",
          "weight": 53.0,
          "weight_reduction": "▲",
          "rank": "11",
          "margin": 1.3,
          "corrected_time": 87.0,
          "running_style": "中",
          "last_3f": 34.6,
          "ave_3f": 36.65,
          "pci": 55.9,
          "position_3f": 0.5
        },
        {
          "date": "2025.9.27",
          "race_name": "１勝ｸﾗｽ",
          "place": "中山",
          "surface": "芝",
          "distance": "2200",
          "track_condition": "良",
          "frame": "6",
          "horse_number": "11",
          "weight": 54.0,
          "weight_reduction": "△",
          "rank": "7",
          "margin": 1.0,
          "corrected_time": 93.0,
          "running_style": "後",
          "last_3f": 34.5,
          "ave_3f": 37.13,
          "pci": 57.6,
          "position_3f": 1.0
        },
        {
          "date": "2025.9.7",
          "race_name": "１勝ｸﾗｽ・牝",
          "place": "札幌",
          "surface": "芝",
          "distance": "1800",
          "track_condition": "稍",
          "frame": "4",
          "horse_number": "5",
          "weight": 53.0,
          "weight_reduction": "▲",
          "rank": "4",
          "margin": 0.3,
          "corrected_time": 96.0,
          "running_style": "後",
          "last_3f": 37.8,
          "ave_3f": 36.65,
          "pci": 47.0,
          "position_3f": 1.9
        },
        {
          "date": "2025.8.23",
          "race_name": "１勝ｸﾗｽ・牝",
          "place": "札幌",
          "surface": "芝",
          "distance": "1800",
          "track_condition": "稍",
          "frame": "2",
          "horse_number": "2",
          "weight": 53.0,
          "weight_reduction": "▲",
          "rank": "9",
          "margin": 1.0,
          "corrected_time": 93.0,
          "running_style": "後",
          "last_3f": 35.7,
          "ave_3f": 37.45,
          "pci": 54.9,
          "position_3f": 1.1
        },
        {
          "date": "2025.8.9",
          "race_name": "１勝ｸﾗｽ",
          "place": "札幌",
          "surface": "芝",
          "distance": "1800",
          "track_condition": "稍",
          "frame": "1",
          "horse_number": "1",
          "weight": 53.0,
          "weight_reduction": "▲",
          "rank": "6",
          "margin": 1.5,
          "corrected_time": 93.0,
          "running_style": "中",
          "last_3f": 36.0,
          "ave_3f": 36.7,
          "pci": 51.9,
          "position_3f": 0.8
        },
        {
          "date": "2025.5.3",
          "race_name": "１勝ｸﾗｽ",
          "place": "京都",
          "surface": "芝",
          "distance": "2200",
          "track_condition": "稍",
          "frame": "6",
          "horse_number": "6",
          "weight": 56.0,
          "weight_reduction": "",
          "rank": "7",
          "margin": 0.9,
          "corrected_time": 90.0,
          "running_style": "マ",
          "last_3f": 34.8,
          "ave_3f": 37.84,
          "pci": 58.7,
          "position_3f": 0.1
        },
        {
          "date": "2025.4.27",
          "race_name": "燧ヶ岳特･1勝",
          "place": "福島",
          "surface": "芝",
          "distance": "2600",
          "track_condition": "良",
          "frame": "5",
          "horse_number": "5",
          "weight": 56.0,
          "weight_reduction": "",
          "rank": "8",
          "margin": 1.5,
          "corrected_time": 85.0,
          "running_style": "後",
          "last_3f": 36.4,
          "ave_3f": 37.11,
          "pci": 52.0,
          "position_3f": 1.0
        },
        {
          "date": "2025.4.12",
          "race_name": "１勝ｸﾗｽ",
          "place": "福島",
          "surface": "芝",
          "distance": "2600",
          "track_condition": "良",
          "frame": "1",
          "horse_number": "2",
          "weight": 56.0,
          "weight_reduction": "",
          "rank": "7",
          "margin": 0.7,
          "corrected_time": 93.0,
          "running_style": "先",
          "last_3f": 35.9,
          "ave_3f": 37.32,
          "pci": 54.0,
          "position_3f": 1.4
        },
        {
          "date": "2025.3.29",
          "race_name": "１勝ｸﾗｽ・牝",
          "place": "中京",
          "surface": "芝",
          "distance": "2000",
          "track_condition": "重",
          "frame": "8",
          "horse_number": "14",
          "weight": 56.0,
          "weight_reduction": "",
          "rank": "9",
          "margin": 1.7,
          "corrected_time": 87.0,
          "running_style": "後",
          "last_3f": 36.9,
          "ave_3f": 36.6,
          "pci": 49.2,
          "position_3f": 1.6
        },
        {
          "date": "2025.3.15",
          "race_name": "１勝ｸﾗｽ",
          "place": "中京",
          "surface": "芝",
          "distance": "2200",
          "track_condition": "良",
          "frame": "8",
          "horse_number": "17",
          "weight": 52.0,
          "weight_reduction": "★",
          "rank": "18",
          "margin": 1.6,
          "corrected_time": 83.0,
          "running_style": "後",
          "last_3f": 35.1,
          "ave_3f": 38.1,
          "pci": 58.5,
          "position_3f": 1.7
        }
      ],
      "indices": {
        "mining_index": 33.57,
        "corrected_time_deviation": 53.45,
        "zi_deviation": 43.19,
        "base_score": 40.98,
        "jockey_coefficient": 0.98047,
        "similarity_coefficient": 1.0045,
        "stability_coefficient": 0.99351,
        "total_coefficient_score": -0.003,
        "final_score": 37.95
      }
    },
    {
      "frame": 5,
      "horse_number": 9,
      "horse_name": "ウーバーストロング",
      "mark": "",
      "jockey": {
        "name": "佐藤翔馬",
        "weight": 53.0,
        "weight_reduction": "▲",
        "this_year": {
          "wins": 4,
          "win_rate": 2.0,
          "place_rate": 4.5,
          "show_rate": 6.1
        },
        "last_year": {
          "wins": 2,
          "win_rate": 1.1,
          "place_rate": 2.2,
          "show_rate": 6.7
        }
      },
      "trainer": {
        "affiliation": "(美)",
        "name": "杉浦宏昭",
        "this_year": {
          "wins": 4,
          "win_rate": 1.8,
          "place_rate": 4.6,
          "show_rate": 11.4
        },
        "last_year": {
          "wins": 11,
          "win_rate": 4.5,
          "place_rate": 8.6,
          "show_rate": 14.8
        }
      },
      "interval": 16,
      "zi_index": 88.0,
      "time_mining": 110.65,
      "battle_mining": 21.9,
      "past_races": [
        {
          "date": "2025.7.22",
          "race_name": "オニキ",
          "place": "盛岡",
          "surface": "芝",
          "distance": "1700",
          "track_condition": "良",
          "frame": "5",
          "horse_number": "6",
          "weight": 53.0,
          "weight_reduction": "▲",
          "rank": "1",
          "margin": -0.7,
          "corrected_time": 0.0,
          "running_style": "逃",
          "last_3f": 0.0,
          "ave_3f": 0.0,
          "pci": 0.0,
          "position_3f": 0.0
        },
        {
          "date": "2025.6.22",
          "race_name": "未勝利",
          "place": "東京",
          "surface": "芝",
          "distance": "1800",
          "track_condition": "良",
          "frame": "7",
          "horse_number": "13",
          "weight": 54.0,
          "weight_reduction": "▲",
          "rank": "6",
          "margin": 1.8,
          "corrected_time": 77.0,
          "running_style": "先",
          "last_3f": 36.4,
          "ave_3f": 35.85,
          "pci": 48.5,
          "position_3f": 0.1
        },
        {
          "date": "2025.4.12",
          "race_name": "山藤賞･1勝*",
          "place": "中山",
          "surface": "芝",
          "distance": "2000",
          "track_condition": "良",
          "frame": "8",
          "horse_number": "9",
          "weight": 57.0,
          "weight_reduction": "",
          "rank": "9",
          "margin": 5.2,
          "corrected_time": 52.0,
          "running_style": "後",
          "last_3f": 40.5,
          "ave_3f": 35.87,
          "pci": 38.6,
          "position_3f": 0.8
        },
        {
          "date": "2025.3.9",
          "race_name": "未勝利",
          "place": "中山",
          "surface": "ダ",
          "distance": "1800",
          "track_condition": "重",
          "frame": "8",
          "horse_number": "15",
          "weight": 57.0,
          "weight_reduction": "",
          "rank": "15",
          "margin": 3.9,
          "corrected_time": 56.0,
          "running_style": "中",
          "last_3f": 43.0,
          "ave_3f": 37.95,
          "pci": 38.3,
          "position_3f": 0.2
        },
        {
          "date": "2025.2.15",
          "race_name": "未勝利",
          "place": "小倉",
          "surface": "芝",
          "distance": "1200",
          "track_condition": "良",
          "frame": "3",
          "horse_number": "6",
          "weight": 54.0,
          "weight_reduction": "▲",
          "rank": "11",
          "margin": 1.8,
          "corrected_time": 84.0,
          "running_style": "中",
          "last_3f": 36.1,
          "ave_3f": 33.7,
          "pci": 43.4,
          "position_3f": 0.6
        },
        {
          "date": "2025.1.25",
          "race_name": "未勝利",
          "place": "中山",
          "surface": "芝",
          "distance": "1600",
          "track_condition": "良",
          "frame": "3",
          "horse_number": "6",
          "weight": 57.0,
          "weight_reduction": "",
          "rank": "7",
          "margin": 0.6,
          "corrected_time": 84.0,
          "running_style": "先",
          "last_3f": 35.3,
          "ave_3f": 36.84,
          "pci": 54.4,
          "position_3f": 0.3
        },
        {
          "date": "2025.1.11",
          "race_name": "未勝利",
          "place": "中山",
          "surface": "芝",
          "distance": "1600",
          "track_condition": "良",
          "frame": "1",
          "horse_number": "1",
          "weight": 57.0,
          "weight_reduction": "",
          "rank": "5",
          "margin": 0.3,
          "corrected_time": 88.0,
          "running_style": "中",
          "last_3f": 36.0,
          "ave_3f": 35.22,
          "pci": 47.8,
          "position_3f": 0.6
        },
        {
          "date": "2024.8.24",
          "race_name": "未勝利*",
          "place": "新潟",
          "surface": "芝",
          "distance": "1600",
          "track_condition": "良",
          "frame": "7",
          "horse_number": "8",
          "weight": 55.0,
          "weight_reduction": "",
          "rank": "7",
          "margin": 1.0,
          "corrected_time": 79.0,
          "running_style": "先",
          "last_3f": 35.4,
          "ave_3f": 36.24,
          "pci": 52.4,
          "position_3f": 0.5
        },
        {
          "date": "2024.8.11",
          "race_name": "新馬",
          "place": "新潟",
          "surface": "芝",
          "distance": "1600",
          "track_condition": "良",
          "frame": "4",
          "horse_number": "4",
          "weight": 52.0,
          "weight_reduction": "▲",
          "rank": "6",
          "margin": 0.5,
          "corrected_time": 83.0,
          "running_style": "中",
          "last_3f": 35.3,
          "ave_3f": 36.6,
          "pci": 53.7,
          "position_3f": 0.3
        }
      ],
      "indices": {
        "mining_index": 27.11,
        "corrected_time_deviation": 50.0,
        "zi_deviation": 38.4,
        "base_score": 35.67,
        "jockey_coefficient": 0.97884,
        "similarity_coefficient": 1.0,
        "stability_coefficient": 1.0,
        "total_coefficient_score": -0.003,
        "final_score": 32.84
      }
    }
  ]
}